CHANGES.txt
MANIFEST.in
README.md
setup.py
plantextract/__init__.py
plantextract/ped.py
plantextract/pedparser.py
plantextract/smdx.py
plantextract/ssparser.py
plantextract/sunspec.py
plantextract.egg-info/PKG-INFO
plantextract.egg-info/SOURCES.txt
plantextract.egg-info/dependency_links.txt
plantextract.egg-info/requires.txt
plantextract.egg-info/top_level.txt
plantextract/smdx/smdx_00001.xml
plantextract/smdx/smdx_00002.xml
plantextract/smdx/smdx_00010.xml
plantextract/smdx/smdx_00011.xml
plantextract/smdx/smdx_00012.xml
plantextract/smdx/smdx_00013.xml
plantextract/smdx/smdx_00014.xml
plantextract/smdx/smdx_00015.xml
plantextract/smdx/smdx_00016.xml
plantextract/smdx/smdx_00017.xml
plantextract/smdx/smdx_00018.xml
plantextract/smdx/smdx_00019.xml
plantextract/smdx/smdx_00101.xml
plantextract/smdx/smdx_00102.xml
plantextract/smdx/smdx_00103.xml
plantextract/smdx/smdx_00111.xml
plantextract/smdx/smdx_00112.xml
plantextract/smdx/smdx_00113.xml
plantextract/smdx/smdx_00120.xml
plantextract/smdx/smdx_00121.xml
plantextract/smdx/smdx_00122.xml
plantextract/smdx/smdx_00123.xml
plantextract/smdx/smdx_00124.xml
plantextract/smdx/smdx_00125.xml
plantextract/smdx/smdx_00126.xml
plantextract/smdx/smdx_00127.xml
plantextract/smdx/smdx_00128.xml
plantextract/smdx/smdx_00129.xml
plantextract/smdx/smdx_00130.xml
plantextract/smdx/smdx_00131.xml
plantextract/smdx/smdx_00132.xml
plantextract/smdx/smdx_00133.xml
plantextract/smdx/smdx_00134.xml
plantextract/smdx/smdx_00201.xml
plantextract/smdx/smdx_00202.xml
plantextract/smdx/smdx_00203.xml
plantextract/smdx/smdx_00204.xml
plantextract/smdx/smdx_00211.xml
plantextract/smdx/smdx_00212.xml
plantextract/smdx/smdx_00213.xml
plantextract/smdx/smdx_00214.xml
plantextract/smdx/smdx_00302.xml
plantextract/smdx/smdx_00303.xml
plantextract/smdx/smdx_00304.xml
plantextract/smdx/smdx_00305.xml
plantextract/smdx/smdx_00306.xml
plantextract/smdx/smdx_00307.xml
plantextract/smdx/smdx_00308.xml
plantextract/smdx/smdx_00401.xml
plantextract/smdx/smdx_00402.xml
plantextract/smdx/smdx_00403.xml
plantextract/smdx/smdx_00404.xml
plantextract/smdx/smdx_00501.xml
plantextract/smdx/smdx_00502.xml
plantextract/smdx/smdx_64001.xml
