Metadata-Version: 1.1
Name: plantextract
Version: 0.2.9
Summary: Python Plant Extract Document processor
Home-page: https://github.com/lashex/ped.git
Author: Brett Francis
Author-email: brett@gridward.com
License: Apache License, Version 2.0
Keywords: sunspec plant extract
Platform: UNKNOWN
Classifier: Development Status :: 2 - Pre-Alpha
Classifier: Intended Audience :: Developers
Classifier: Intended Audience :: Other Audience
Classifier: Natural Language :: English
Classifier: Programming Language :: Python
Classifier: Topic :: Utilities
Classifier: Topic :: Software Development
Classifier: Topic :: Text Processing :: Markup :: XML
Classifier: Operating System :: OS Independent
